{
    "ActiveSlot": true,
    "SlotId": 2,
    "numSessions": 0,
    "score": 25,
    "playtime": 0,
    "inventory": {
        "Dark Fruit": 22,
        "Hero Fruit": 7,
        "T.V.": 1,
        "Green Fruit": 4,
        "Red Fruit": 5,
        "Blue Fruit": 4,
        "Duck": 2,
        "Trumpet": 4
    },
    "averagePlaytime": 0,
    "chao": {
        "name": "Chao",
        "state": "NORMAL",
        "type": "DARK",
        "alignment": -7,
        "status": {
            "sleep": 31,
            "happiness": 34,
            "fullness": 64,
            "health": 100
        }
    }
}